airway/__init__.py
airway/analysis/__init__.py
airway/analysis/analyze_tree.py
airway/analysis/create_color_masks.py
airway/analysis/data_quality_evaluation.py
airway/analysis/metadata.py
airway/analysis/plot_connected_lobes_status.py
airway/classification/__init__.py
airway/classification/angle_analysis.py
airway/classification/clustering.py
airway/classification/lobe_validation.py
airway/classification/segment_validation.py
airway/classification/split_classification.py
airway/cli/__init__.py
airway/cli/base.py
airway/cli/cli.py
airway/cli/config.py
airway/cli/run_example.py
airway/cli/stages.py
airway/cli/tutorial.py
airway/cli/visualization.py
airway/configs/__init__.py
airway/configs/array_encoding.yaml
airway/configs/classification.yaml
airway/configs/example_defaults.yaml
airway/configs/stage_configs.yaml
airway/data_generation/__init__.py
airway/data_generation/create_dummy_bronchus.py
airway/example_data/model.npz
airway/image_processing/__init__.py
airway/image_processing/generate_bronchus_coords.py
airway/image_processing/remove_all_0_layers.py
airway/image_processing/save_images_as_npz.py
airway/obj_generation/__init__.py
airway/obj_generation/gen_obj.py
airway/obj_generation/gen_split_obj.py
airway/tree_extraction/__init__.py
airway/tree_extraction/bfs_distance_method.py
airway/tree_extraction/compose_tree.py
airway/tree_extraction/create_tree.py
airway/tree_extraction/post_processing.py
airway/tree_extraction/separate_lobes.py
airway/util/__init__.py
airway/util/color.py
airway/util/config_parsers.py
airway/util/const.py
airway/util/helper_functions.py
airway/util/parsing.py
airway/util/util.py
airway/visualization/__init__.py
airway/visualization/analyse_dist_to_coords.py
airway/visualization/create_website.py
airway/visualization/generate_2d_tree.py
airway/visualization/plot_dist_animation.py
airway/visualization/plot_dist_to_first_split.py
airway/visualization/plot_isometric.py
airway/visualization/plot_lobes.py
airway/visualization/plot_splits.py
airway-0.2.3.dist-info/LICENSE
airway-0.2.3.dist-info/METADATA
airway-0.2.3.dist-info/WHEEL
airway-0.2.3.dist-info/entry_points.txt
airway-0.2.3.dist-info/top_level.txt
airway-0.2.3.dist-info/RECORD
