Metadata-Version: 2.1
Name: airway
Version: 0.2.3
Summary: Automatic classification of tertiary bronchi based on bronchus masks using a rule-based approach.
Home-page: https://github.com/LiquidFun/Airway
Author: Brutenis Gliwa
License: GPL-3.0
Classifier: License :: OSI Approved :: GNU General Public License v3 (GPLv3)
Classifier: Programming Language :: Python
Classifier: Programming Language :: Python :: 3
Classifier: Programming Language :: Python :: 3.6
Classifier: Programming Language :: Python :: Implementation :: CPython
Classifier: Topic :: Scientific/Engineering :: Medical Science Apps.
Requires-Python: >=3.6
License-File: LICENSE
Requires-Dist: numpy
Requires-Dist: pydicom
Requires-Dist: networkx
Requires-Dist: scikit-image
Requires-Dist: pandas
Requires-Dist: pyyaml
Requires-Dist: matplotlib
Requires-Dist: tqdm
Requires-Dist: Markdown
Requires-Dist: weasyprint
Requires-Dist: pytest
Requires-Dist: py2cytoscape
